data_extractor/__init__.py
data_extractor/contrib/mypy/__init__.py
data_extractor/core.py
data_extractor/exceptions.py
data_extractor/item.py
data_extractor/json.py
data_extractor/lxml.py
data_extractor/py.typed
data_extractor/utils.py
data_extractor-1.0.1.dist-info/WHEEL
data_extractor-1.0.1.dist-info/METADATA
data_extractor-1.0.1.dist-info/licenses/LICENSE
data_extractor-1.0.1.dist-info/RECORD
