Metadata-Version: 2.1
Name: data_extractor
Version: 1.0.1
Summary: Combine XPath, CSS Selectors and JSONPath for Web data extracting.
License: MIT
Keywords: data-extractor,data-extraction,xpath,css-selectors,jsonpath
Author-email: 林玮 (Jade Lin) <linw1995@icloud.com>
Requires-Python: >=3.9
Classifier: Development Status :: 5 - Production/Stable
Classifier: Intended Audience :: Developers
Classifier: License :: OSI Approved :: MIT License
Classifier: Operating System :: MacOS :: MacOS X
Classifier: Operating System :: Microsoft :: Windows
Classifier: Operating System :: POSIX
Classifier: Programming Language :: Python
Classifier: Programming Language :: Python :: 3
Classifier: Programming Language :: Python :: 3.10
Classifier: Programming Language :: Python :: 3.11
Classifier: Programming Language :: Python :: 3.12
Classifier: Programming Language :: Python :: 3.13
Classifier: Programming Language :: Python :: 3.9
Provides-Extra: cssselect
Requires-Dist: lxml<6,>=4.3; extra == "cssselect"
Requires-Dist: cssselect<2,>=1.0.3; extra == "cssselect"
Provides-Extra: jsonpath-extractor
Requires-Dist: jsonpath-extractor<0.9,>=0.5; extra == "jsonpath-extractor"
Provides-Extra: jsonpath-rw
Requires-Dist: jsonpath-rw<2,>=1.4; extra == "jsonpath-rw"
Provides-Extra: jsonpath-rw-ext
Requires-Dist: jsonpath-rw<2,>=1.4; extra == "jsonpath-rw-ext"
Requires-Dist: jsonpath-rw-ext<2,>=1.2; extra == "jsonpath-rw-ext"
Provides-Extra: lxml
Requires-Dist: lxml<6,>=4.3; extra == "lxml"
Project-URL: documentation, https://data-extractor.readthedocs.io/en/latest/
Project-URL: homepage, https://github.com/linw1995/data_extractor
Project-URL: repository, https://github.com/linw1995/data_extractor
